README.md
pltvid.py
setup.py
pltvid.egg-info/PKG-INFO
pltvid.egg-info/SOURCES.txt
pltvid.egg-info/dependency_links.txt
pltvid.egg-info/requires.txt
pltvid.egg-info/top_level.txt